README.md
setup.cfg
setup.py
jetbrains_issues_dataset/__init__.py
jetbrains_issues_dataset.egg-info/PKG-INFO
jetbrains_issues_dataset.egg-info/SOURCES.txt
jetbrains_issues_dataset.egg-info/dependency_links.txt
jetbrains_issues_dataset.egg-info/top_level.txt
jetbrains_issues_dataset/idea/__init__.py
jetbrains_issues_dataset/idea/activity_manager.py
jetbrains_issues_dataset/idea/download_activities.py
jetbrains_issues_dataset/idea/first_assignee_snapshot_strategy.py
jetbrains_issues_dataset/idea/idea_activity_manager.py
jetbrains_issues_dataset/idea/idea_data_set.py
jetbrains_issues_dataset/idea/issue_created_snapshot_strategy.py
jetbrains_issues_dataset/idea/snapshot_strategy.py
jetbrains_issues_dataset/idea/youtrack.py