Metadata-Version: 2.1
Name: jetbrains-issues-dataset
Version: 1.0.4
Summary: Dataset of JetBrains issues
Home-page: https://github.com/avokin2/jetbrains-issues-dataset
Author: Andrey Vokin
Author-email: andrey.vokin@gmail.com
License: MIT
Download-URL: https://github.com/avokin2/jetbrains-issues-dataset/archive/v_1.0.4.tar.gz
Platform: UNKNOWN
Classifier: Development Status :: 5 - Production/Stable
Classifier: Intended Audience :: Developers
Classifier: Topic :: Software Development :: Build Tools
Classifier: License :: OSI Approved :: MIT License
Classifier: Programming Language :: Python :: 3
Classifier: Programming Language :: Python :: 3.4
Classifier: Programming Language :: Python :: 3.5
Classifier: Programming Language :: Python :: 3.6
Classifier: Programming Language :: Python :: 3.7
